{
  "members": [
    {
      "id": 1,
      "avatar_url": "https://images.unsplash.com/photo-1534438327276-14e5300c3a48?ixlib=rb-1.2.1&ixid=eyJhcHBfaWQiOjEyMDd9&auto=format&fit=crop&w=1050&q=80",
      "name": "Gabriel Caiana",
      "email": "gabrielcaianaguedes@gmail.com",
      "birth": 849052800000,
      "gender": "M",
      "blood": "O+",
      "weight": "95",
      "height": "188"
    }
  ],
  "instructors": [
    {
      "id": 2,
      "name": "Maria silva",
      "avatar_url": "https://images.unsplash.com/photo-1434682966726-19ad3a76e143?ixlib=rb-1.2.1&ixid=eyJhcHBfaWQiOjEyMDd9&auto=format&fit=crop&w=1053&q=80",
      "birth": 433987200000,
      "gender": "F",
      "services": "Musculação, cardio, Pilates",
      "created_At": 1587101640007
    },
    {
      "id": 3,
      "name": "Gisely Almeida",
      "avatar_url": "https://scontent.fcgh5-1.fna.fbcdn.net/v/t1.0-9/67379563_2389083184517306_4568553049148096512_o.jpg?_nc_cat=105&_nc_sid=84a396&_nc_ohc=ZOM9VDe-3OQAX8eiqM7&_nc_pt=1&_nc_ht=scontent.fcgh5-1.fna&oh=94ff4b9fc7dce291ff0257697a79368d&oe=5EBF8325",
      "birth": 793238400000,
      "gender": "F",
      "services": "Pilates, Ioga, corrida",
      "created_At": 1587101670290
    },
    {
      "id": 4,
      "name": "Gabriel Caiana Guedes",
      "avatar_url": "https://scontent.fcgh4-1.fna.fbcdn.net/v/t1.0-9/s960x960/78334707_165107608223078_432012687082258432_o.jpg?_nc_cat=111&_nc_sid=84a396&_nc_eui2=AeFKCUEtGK07ymEFCmG-Xtlb79wab_2ksVrv3Bpv_aSxWjxSwFJXj6ywXBoCRzEUevDmMmThCJWA7kyGL6IbrJXN&_nc_ohc=Q8Rm0nyIMN0AX_xVebP&_nc_pt=1&_nc_ht=scontent.fcgh4-1.fna&_nc_tp=7&oh=a079a9923d560653b7eadcb675ab8c33&oe=5EC1FFFA",
      "birth": 849052800000,
      "gender": "M",
      "services": "Crossfit, Natação, Musculação",
      "created_At": 1587318065942
    },
    {
      "id": 4,
      "name": "Polly Caiana",
      "avatar_url": "https://images.unsplash.com/photo-1534438327276-14e5300c3a48?ixlib=rb-1.2.1&ixid=eyJhcHBfaWQiOjEyMDd9&auto=format&fit=crop&w=1050&q=80",
      "birth": 1545523200000,
      "gender": "F",
      "services": "Crossfit, musculação",
      "created_At": 1587508120624
    }
  ]
}